mand/__init__.py
mand/__main__.py
mand/mand.py
mand/util.py
mand-0.9.8.dist-info/METADATA
mand-0.9.8.dist-info/RECORD
mand-0.9.8.dist-info/WHEEL
mand-0.9.8.dist-info/entry_points.txt
mand-0.9.8.dist-info/top_level.txt
mand-0.9.8.dist-info/zip-safe
