Metadata-Version: 2.1
Name: mand
Version: 0.9.8
Summary: Run multiple modules with the same interpreter
Home-page: https://github.com/brycepg/mand
Author: Bryce Guinta
Author-email: contact@bryceguinta.me
License: MIT
Platform: UNKNOWN
Classifier: Programming Language :: Python :: 3 :: Only
Classifier: Programming Language :: Python :: 3.4
Classifier: Programming Language :: Python :: 3.5
Classifier: Programming Language :: Python :: 3.6
Classifier: Intended Audience :: Developers
Classifier: License :: OSI Approved :: MIT License
Classifier: Topic :: Software Development :: Libraries
